{
  "task_id": "2026-06-16-feature-complex-coding-harness-plan-self-review",
  "task_dir": ".harness/tasks/2026-06-16/feature/complex-coding-harness-plan-self-review",
  "title": "complex-coding-harness 规划自查独立模块",
  "status": "completed",
  "execution_mode": "run-to-completion",
  "overall_status": "completed",
  "current_stage": "Final Delivery",
  "remaining_stages": [],
  "next_action": "任务完成；等待用户验收或后续使用反馈",
  "next_automatic_action": "none",
  "stop_condition": "all_approved_stages_completed",
  "state_source": "execution-plan.md",
  "planning_review": {
    "status": "pass",
    "defects": "fixed",
    "missing_items": "fixed",
    "optimizations": "fixed",
    "consistency": "fixed",
    "latest_review": "已修复模板门禁顺序缺陷，要求实施时调整为 Plan Quality Gate -> Plan Self-Review -> Readiness Gate -> Plan Approval",
    "updated_at": "2026-06-16"
  },
  "updated_at": "2026-06-16"
}
